MANIFEST.in
README.md
requirements.txt
setup.py
tests/__init__.py
tests/test_comment.py
translate_comment_out/__init__.py
translate_comment_out/comment.py
translate_comment_out/config.py
translate_comment_out/main.py
translate_comment_out/sample.py
translate_comment_out/translator.py
translate_comment_out.egg-info/PKG-INFO
translate_comment_out.egg-info/SOURCES.txt
translate_comment_out.egg-info/dependency_links.txt
translate_comment_out.egg-info/entry_points.txt
translate_comment_out.egg-info/requires.txt
translate_comment_out.egg-info/top_level.txt