Metadata-Version: 2.1
Name: translate-comment-out
Version: 1.2
Summary: Translate Comment Out
Home-page: https://github.com/koboriakira/translate_comment_out
Author: Kobori Akira
Author-email: private.beats@gmail.com
License: UNKNOWN
Platform: UNKNOWN
